Metadata-Version: 2.1
Name: catalogo-cp-mex
Version: 0.0.2
Summary: Permite migrar los codigos postales de México
Home-page: UNKNOWN
License: UNKNOWN
Platform: UNKNOWN
